nptracer/__init__.py
nptracer/changaLoader.py
nptracer/dataAnalyzer.py
nptracer/dataLoader.py
nptracer/driver.py
nptracer/gengaLoader.py
Nptracer-0.0.2.dist-info/LICENSE
Nptracer-0.0.2.dist-info/METADATA
Nptracer-0.0.2.dist-info/WHEEL
Nptracer-0.0.2.dist-info/top_level.txt
Nptracer-0.0.2.dist-info/RECORD
