Metadata-Version: 2.1
Name: Nptracer
Version: 0.0.2
License-File: LICENSE
Requires-Dist: numpy
Requires-Dist: pandas
Requires-Dist: pynbody
Requires-Dist: KeplerOrbit
